oxentiel/__init__.py
oxentiel/oxentiel.py
oxentiel/pprint.py
oxentiel-0.0.1.dist-info/LICENSE
oxentiel-0.0.1.dist-info/METADATA
oxentiel-0.0.1.dist-info/WHEEL
oxentiel-0.0.1.dist-info/top_level.txt
oxentiel-0.0.1.dist-info/RECORD
