Metadata-Version: 2.1
Name: oxentiel
Version: 0.0.1
Summary: A configuration object to replace settings dictionaries.
Home-page: UNKNOWN
Author: Brendan Whitaker
License: GPLv3
Platform: UNKNOWN
Classifier: Development Status :: 3 - Alpha
Classifier: Intended Audience :: Developers
Classifier: Intended Audience :: Education
Classifier: Intended Audience :: Science/Research
Classifier: Topic :: Utilities
Classifier: License :: OSI Approved :: BSD License
Classifier: Topic :: Scientific/Engineering
Classifier: Programming Language :: Python :: 3.7
Requires-Python: >=3.7.0
